CHANGELOG.rst
MANIFEST.in
README.rst
setup.cfg
setup.py
theo/__init__.py
theo.recipe.cmd.egg-info/PKG-INFO
theo.recipe.cmd.egg-info/SOURCES.txt
theo.recipe.cmd.egg-info/dependency_links.txt
theo.recipe.cmd.egg-info/entry_points.txt
theo.recipe.cmd.egg-info/namespace_packages.txt
theo.recipe.cmd.egg-info/not-zip-safe
theo.recipe.cmd.egg-info/requires.txt
theo.recipe.cmd.egg-info/top_level.txt
theo/recipe/__init__.py
theo/recipe/cmd/__init__.py