Metadata-Version: 1.1
Name: theo.recipe.cmd
Version: 0.6.2
Summary: ZC Buildout recipe to execute commands in it's own shell
Home-page: https://github.com/timonwong/theo.recipe.cmd
Author: Timon Wong
Author-email: timon86.wang@gmail.com
License: GPL
Keywords: buildout,zc.buildout,recipe
Platform: UNKNOWN
Classifier: Programming Language :: Python
Classifier: Topic :: Software Development :: Libraries :: Python Modules
Classifier: Framework :: Buildout
